{
	"credit": "Made with Blockbench",
	"texture_size": [128, 128],
	"textures": {
		"2": "mcx",
		"particle": "mcx"
	},
	"elements": [
		{
			"from": [7.93843, 9.2106, 9.02796],
			"to": [8.8197, 9.90303, 10.28691],
			"rotation": {"angle": 0, "axis": "y", "origin": [7.82789, 7.97773, 8.57299]},
			"faces": {
				"north": {"uv": [1.375, 8.625, 1.5, 8.6875], "texture": "#2"},
				"east": {"uv": [8.125, 7.875, 8.3125, 7.9375], "texture": "#2"},
				"south": {"uv": [8.625, 1.375, 8.75, 1.4375], "texture": "#2"},
				"down": {"uv": [6.25, 7.25, 6.125, 7.4375], "texture": "#2"}
			}
		},
		{
			"from": [9.26111, 8.6378, 9.02796],
			"to": [9.89059, 9.33023, 10.28691],
			"rotation": {"angle": 45, "axis": "z", "origin": [7.82789, 7.97773, 8.57299]},
			"faces": {
				"north": {"uv": [4.5, 9.5, 4.5625, 9.5625], "texture": "#2"},
				"east": {"uv": [8.125, 8, 8.3125, 8.0625], "texture": "#2"},
				"south": {"uv": [9.5, 4.5, 9.5625, 4.5625], "texture": "#2"},
				"up": {"uv": [8.1875, 8.3125, 8.125, 8.125], "texture": "#2"}
			}
		},
		{
			"from": [8.19022, 9.2106, 12.80483],
			"to": [8.8197, 9.90303, 14.06379],
			"rotation": {"angle": 0, "axis": "y", "origin": [7.82789, 7.97773, 8.57299]},
			"faces": {
				"north": {"uv": [4.625, 9.5, 4.6875, 9.5625], "texture": "#2"},
				"east": {"uv": [0, 8.25, 0.1875, 8.3125], "texture": "#2"},
				"south": {"uv": [9.5, 4.625, 9.5625, 4.6875], "texture": "#2"},
				"west": {"uv": [8.25, 0, 8.4375, 0.0625], "texture": "#2"},
				"down": {"uv": [8.3125, 0.125, 8.25, 0.3125], "texture": "#2"}
			}
		},
		{
			"from": [9.26111, 8.6378, 12.80483],
			"to": [9.89059, 9.33023, 14.06379],
			"rotation": {"angle": 45, "axis": "z", "origin": [7.82789, 7.97773, 8.57299]},
			"faces": {
				"north": {"uv": [4.75, 9.5, 4.8125, 9.5625], "texture": "#2"},
				"east": {"uv": [0.25, 8.25, 0.4375, 8.3125], "texture": "#2"},
				"south": {"uv": [9.5, 4.75, 9.5625, 4.8125], "texture": "#2"},
				"west": {"uv": [8.25, 0.5, 8.4375, 0.5625], "texture": "#2"},
				"up": {"uv": [0.5625, 8.4375, 0.5, 8.25], "texture": "#2"}
			}
		},
		{
			"from": [7.18305, 9.2106, 9.02796],
			"to": [8.06432, 9.90303, 10.28691],
			"rotation": {"angle": 0, "axis": "y", "origin": [7.82789, 7.97773, 8.57299]},
			"faces": {
				"north": {"uv": [1.5, 8.625, 1.625, 8.6875], "texture": "#2"},
				"south": {"uv": [8.625, 1.5, 8.75, 1.5625], "texture": "#2"},
				"west": {"uv": [8.25, 0.625, 8.4375, 0.6875], "texture": "#2"},
				"down": {"uv": [6.625, 7.25, 6.5, 7.4375], "texture": "#2"}
			}
		},
		{
			"from": [6.01053, 8.88315, 9.02796],
			"to": [6.64001, 9.57558, 10.28691],
			"rotation": {"angle": -45, "axis": "z", "origin": [7.82789, 7.97773, 8.57299]},
			"faces": {
				"north": {"uv": [4.875, 9.5, 4.9375, 9.5625], "texture": "#2"},
				"south": {"uv": [9.5, 4.875, 9.5625, 4.9375], "texture": "#2"},
				"west": {"uv": [0.75, 8.25, 0.9375, 8.3125], "texture": "#2"}
			}
		},
		{
			"from": [7.18305, 9.2106, 12.80483],
			"to": [7.81253, 9.90303, 14.06379],
			"rotation": {"angle": 0, "axis": "y", "origin": [7.82789, 7.97773, 8.57299]},
			"faces": {
				"north": {"uv": [5, 9.5, 5.0625, 9.5625], "texture": "#2"},
				"east": {"uv": [8.25, 0.875, 8.4375, 0.9375], "texture": "#2"},
				"south": {"uv": [9.5, 5, 9.5625, 5.0625], "texture": "#2"},
				"west": {"uv": [1, 8.25, 1.1875, 8.3125], "texture": "#2"},
				"down": {"uv": [1.3125, 8.25, 1.25, 8.4375], "texture": "#2"}
			}
		},
		{
			"from": [6.01053, 8.88315, 12.80483],
			"to": [6.64001, 9.57558, 14.06379],
			"rotation": {"angle": -45, "axis": "z", "origin": [7.82789, 7.97773, 8.57299]},
			"faces": {
				"north": {"uv": [5.125, 9.5, 5.1875, 9.5625], "texture": "#2"},
				"east": {"uv": [1.375, 8.25, 1.5625, 8.3125], "texture": "#2"},
				"south": {"uv": [9.5, 5.125, 9.5625, 5.1875], "texture": "#2"},
				"west": {"uv": [1.625, 8.25, 1.8125, 8.3125], "texture": "#2"}
			}
		},
		{
			"from": [6.72979, 8.92227, 10.28691],
			"to": [7.04453, 10.05533, 12.86778],
			"rotation": {"angle": -22.5, "axis": "z", "origin": [7.82789, 7.97773, 8.57299]},
			"faces": {
				"north": {"uv": [1.625, 8.625, 1.6875, 8.75], "texture": "#2"},
				"east": {"uv": [6.625, 1.125, 6.9375, 1.25], "texture": "#2"},
				"south": {"uv": [8.625, 1.625, 8.6875, 1.75], "texture": "#2"},
				"west": {"uv": [6.625, 1.25, 6.9375, 1.375], "texture": "#2"},
				"up": {"uv": [7.5625, 6.0625, 7.5, 5.75], "texture": "#2"},
				"down": {"uv": [6.1875, 7.5, 6.125, 7.8125], "texture": "#2"}
			}
		},
		{
			"from": [8.93181, 8.78949, 10.28691],
			"to": [9.24655, 9.92255, 12.86778],
			"rotation": {"angle": 22.5, "axis": "z", "origin": [7.82789, 7.97773, 8.57299]},
			"faces": {
				"north": {"uv": [1.75, 8.625, 1.8125, 8.75], "texture": "#2"},
				"east": {"uv": [6.625, 1.875, 6.9375, 2], "texture": "#2"},
				"south": {"uv": [8.625, 1.75, 8.6875, 1.875], "texture": "#2"},
				"west": {"uv": [6.625, 2, 6.9375, 2.125], "texture": "#2"},
				"up": {"uv": [7.5625, 6.4375, 7.5, 6.125], "texture": "#2"},
				"down": {"uv": [6.3125, 7.5, 6.25, 7.8125], "texture": "#2"}
			}
		},
		{
			"from": [7.67267, 9.70022, 9.02796],
			"to": [8.32733, 10.39265, 10.28691],
			"rotation": {"angle": 0, "axis": "y", "origin": [7.82789, 7.97773, 8.57299]},
			"faces": {
				"north": {"uv": [5.25, 9.5, 5.3125, 9.5625], "texture": "#2"},
				"east": {"uv": [1.875, 8.25, 2.0625, 8.3125], "texture": "#2"},
				"south": {"uv": [9.5, 5.25, 9.5625, 5.3125], "texture": "#2"},
				"up": {"uv": [2.1875, 8.4375, 2.125, 8.25], "texture": "#2"}
			}
		},
		{
			"from": [7.67267, 9.70022, 12.80483],
			"to": [8.32733, 10.39265, 14.06379],
			"rotation": {"angle": 0, "axis": "y", "origin": [7.82789, 7.97773, 8.57299]},
			"faces": {
				"north": {"uv": [5.375, 9.5, 5.4375, 9.5625], "texture": "#2"},
				"east": {"uv": [2.25, 8.25, 2.4375, 8.3125], "texture": "#2"},
				"south": {"uv": [9.5, 5.375, 9.5625, 5.4375], "texture": "#2"},
				"up": {"uv": [2.5625, 8.4375, 2.5, 8.25], "texture": "#2"},
				"down": {"uv": [8.3125, 2.5, 8.25, 2.6875], "texture": "#2"}
			}
		},
		{
			"from": [7.6111, 9.18435, 10.28691],
			"to": [8.39165, 10.31741, 12.86778],
			"rotation": {"angle": 0, "axis": "y", "origin": [7.82789, 7.97773, 8.57299]},
			"faces": {
				"north": {"uv": [1.75, 7.75, 1.875, 7.875], "texture": "#2"},
				"east": {"uv": [6.625, 2.625, 6.9375, 2.75], "texture": "#2"},
				"south": {"uv": [1.875, 7.75, 2, 7.875], "texture": "#2"},
				"west": {"uv": [6.625, 2.75, 6.9375, 2.875], "texture": "#2"},
				"up": {"uv": [1.75, 6.9375, 1.625, 6.625], "texture": "#2"},
				"down": {"uv": [2.375, 6.625, 2.25, 6.9375], "texture": "#2"}
			}
		}
	],
	"display": {
		"thirdperson_righthand": {
			"translation": [0, 0.5, -3.25],
			"scale": [0.55, 0.55, 0.55]
		},
		"thirdperson_lefthand": {
			"translation": [0, 0.5, -3.25],
			"scale": [0.55, 0.55, 0.55]
		},
		"firstperson_righthand": {
			"translation": [-6, 3.5, -2]
		},
		"firstperson_lefthand": {
			"translation": [-6, 3.5, -2]
		},
		"ground": {
			"translation": [0, 3, 0],
			"scale": [0.55, 0.55, 0.55]
		},
		"gui": {
			"rotation": [30, -145, 0],
			"translation": [1.25, -1, 0],
			"scale": [0.75, 0.75, 0.75]
		},
		"fixed": {
			"rotation": [0, 90, 0],
			"translation": [-5, -0.5, -2],
			"scale": [1.1, 1.1, 1.1]
		}
	},
	"groups": [
		{
			"name": "bolt",
			"origin": [7.9075, 5.31457, 8.2875],
			"color": 0,
			"children": [0, 1, 2, 3, 4, 5, 6, 7, 8, 9, 10, 11, 12]
		}
	]
}